kcache/__init__.py
kcache/basecache.py
kcache/cache.py
kcache/cache_builder.py
kcache/cacheloader.py
kcache/loading_cache.py
kcache-0.0.3.dist-info/METADATA
kcache-0.0.3.dist-info/WHEEL
kcache-0.0.3.dist-info/top_level.txt
kcache-0.0.3.dist-info/RECORD
