Metadata-Version: 2.1
Name: kcache
Version: 0.0.3
Summary: Cache Library
Home-page: https://github.com/krzysbaranski/kcache
Author: Krzysztof Baranski
Author-email: baranski5@gmail.com
License: GNU Lesser General Public License Version 3
Platform: UNKNOWN
Classifier: Programming Language :: Python :: 3
Classifier: Topic :: Software Development :: Libraries
Classifier: Typing :: Typed
Requires-Python: >=3.7
Provides-Extra: test
Requires-Dist: pytest (==6.1.1) ; extra == 'test'
